payton/__init__.py
payton/math/__init__.py
payton/math/functions.py
payton/math/geometry.py
payton/math/matrix.py
payton/math/types.py
payton/math/vector.py
payton/scene/__init__.py
payton/scene/camera.py
payton/scene/clock.py
payton/scene/collision.py
payton/scene/controller.py
payton/scene/grid.py
payton/scene/gtk.py
payton/scene/gtkcontroller.py
payton/scene/light.py
payton/scene/material.py
payton/scene/particle.png
payton/scene/physics.py
payton/scene/receiver.py
payton/scene/scene.py
payton/scene/shader.py
payton/scene/types.py
payton/scene/font/Glametrix.otf
payton/scene/geometry/__init__.py
payton/scene/geometry/awp3d.py
payton/scene/geometry/base.py
payton/scene/geometry/cube.py
payton/scene/geometry/cylinder.py
payton/scene/geometry/export.py
payton/scene/geometry/md2.py
payton/scene/geometry/mesh.py
payton/scene/geometry/particle.py
payton/scene/geometry/plane.py
payton/scene/geometry/ragdoll.py
payton/scene/geometry/sphere.py
payton/scene/geometry/wavefront.py
payton/scene/gui/__init__.py
payton/scene/gui/base.py
payton/scene/gui/help.py
payton/scene/gui/monofonto.ttf
payton/scene/gui/window.py
payton/tools/__init__.py
payton/tools/bar.py
payton/tools/mesh/__init__.py
payton/tools/mesh/geometry.py
payton/tools/mesh/line.py
payton-1.3.3.dist-info/LICENSE
payton-1.3.3.dist-info/METADATA
payton-1.3.3.dist-info/WHEEL
payton-1.3.3.dist-info/top_level.txt
payton-1.3.3.dist-info/RECORD
