Metadata-Version: 2.2
Name: Payton
Version: 1.3.3
Summary: "3D Graphics Programming Toolkit"
Home-page: https://github.com/sinanislekdemir/payton
Author: Sinan Islekdemir
Author-email: sinan@islekdemir.com
Classifier: Programming Language :: Python :: 3
Classifier: License :: OSI Approved :: BSD License
Classifier: Operating System :: OS Independent
Requires-Python: >=3.10
License-File: LICENSE
Requires-Dist: Pillow>=10.3.0
Requires-Dist: PyOpenGL>=3.1.7
Requires-Dist: pyrr>=0.10.3
Requires-Dist: PySDL2>=0.9.16
Requires-Dist: Cython>=3.0.5
Requires-Dist: numpy>=1.26.4
